{
    "gdino": {
        "1": "2"
    },
    "gdino_readable": {
        "1": "Nintendo DS Lite Console"
    },
    "gdino_token_counts": {
        "1": {
            "nintendo": 59,
            "dsi": 45,
            "nintendo dsi": 42,
            "console": 37,
            "black": 31,
            "ds": 18,
            "japan": 16,
            "nintendo ds": 13,
            "tested": 12,
            "charger": 11,
            "edition": 11,
            "001": 9,
            "japanese": 9,
            "game": 9,
            "lite": 9,
            "ds lite": 9,
            "handheld": 9,
            "dsi black": 8,
            "dsi console": 8,
            "box": 8,
            "ver": 8,
            "saga": 7,
            "2": 7,
            "pokemon": 6,
            "system": 6,
            "black console": 6,
            "xl": 5,
            "dsi xl": 5,
            "handheld system": 5,
            "edition black": 5,
            "20th": 4,
            "anniversary": 4,
            "dsi saga": 4,
            "saga 20th": 4,
            "20th anniversary": 4,
            "black japan": 4,
            "japan console": 4,
            "twl": 4,
            "twl 001": 4,
            "console japanese": 4,
            "pen": 4,
            "console black": 4,
            "resilam": 4,
            "zechrome": 4,
            "dsi resilam": 4,
            "resilam zechrome": 4,
            "zechrome edition": 4,
            "manual": 4,
            "japanese ver": 4,
            "game console": 4,
            "used": 4,
            "limited": 3,
            "goddess": 3,
            "destiny": 3,
            "saga 2": 3,
            "goddess destiny": 3,
            "destiny saga": 3,
            "anniversary console": 3,
            "utl": 3,
            "utl 001": 3,
            "ntsc": 3,
            "w": 3,
            "kingdom": 3,
            "hearts": 3,
            "set": 3,
            "kingdom hearts": 3,
            "hearts edition": 3,
            "black handheld": 3,
            "various": 3,
            "colors": 3,
            "various colors": 3,
            "black box": 3,
            "3": 3
        }
    }
}