{
    "gdino": {
        "1": "17",
        "2": "11",
        "3": "17",
        "4": "11"
    },
    "gdino_readable": {
        "1": "Gamecube Controller",
        "2": "Nintendo Game Boy Color Console",
        "3": "Gamecube Controller",
        "4": "Nintendo Game Boy Color Console"
    },
    "gdino_token_counts": {
        "1": {
            "gamecube": 10,
            "controller": 10,
            "nintendo": 8,
            "gamecube controller": 7,
            "nintendo gamecube": 6,
            "black": 3,
            "gc": 3,
            "various": 3,
            "colors": 3,
            "com": 2
        },
        "2": {
            "gamecube": 42,
            "controller": 40,
            "nintendo": 39,
            "nintendo gamecube": 29,
            "gamecube controller": 23,
            "purple": 15,
            "indigo": 13,
            "dol": 13,
            "003": 13,
            "dol 003": 13,
            "oem": 12,
            "controller indigo": 9,
            "original": 9,
            "game": 9,
            "tested": 8,
            "wii": 7,
            "gc": 7,
            "switch": 6,
            "authentic": 6,
            "console": 5,
            "violet": 5,
            "ngc": 5,
            "2": 5,
            "003 tested": 5,
            "games": 4,
            "console controller": 4,
            "cube": 4,
            "pad": 4,
            "game cube": 4,
            "nintendo switch": 4,
            "genuine": 4,
            "controller purple": 4,
            "com": 3,
            "color": 3,
            "gamecube console": 3,
            "controller violet": 3,
            "clear": 3,
            "purple clear": 3,
            "original nintendo": 3,
            "wired": 3,
            "gamecube wii": 3,
            "classic": 3,
            "working": 3,
            "tested working": 3,
            "adapter": 3,
            "japan": 3,
            "oem nintendo": 3,
            "indigo purple": 3,
            "purple dol": 3
        },
        "3": {
            "gamecube": 11,
            "controller": 10,
            "nintendo": 8,
            "gamecube controller": 7,
            "nintendo gamecube": 6,
            "black": 4,
            "smash": 4,
            "bros": 4
        },
        "4": {
            "gamecube": 50,
            "nintendo": 48,
            "controller": 40,
            "nintendo gamecube": 39,
            "silver": 31,
            "gamecube controller": 21,
            "console": 15,
            "tested": 13,
            "dol": 12,
            "platinum": 11,
            "controller silver": 11,
            "oem": 10,
            "003": 9,
            "dol 003": 8,
            "game": 8,
            "bundle": 6,
            "2": 6,
            "black": 5,
            "japan": 5,
            "gamecube silver": 5,
            "set": 5,
            "wii": 5,
            "works": 4,
            "gc": 4,
            "choose": 4,
            "rare": 4,
            "1": 4,
            "wired": 4,
            "controllers": 4,
            "system": 4,
            "silver console": 4,
            "console bundle": 4,
            "color": 4,
            "003 tested": 3,
            "w": 3,
            "boxed": 3,
            "gamecube console": 3,
            "platinum silver": 3,
            "controller dol": 3,
            "001": 3,
            "4": 3,
            "read": 3,
            "dol 001": 3,
            "plus": 3,
            "pack": 3,
            "jp": 3,
            "gamecube platinum": 3,
            "gamecube wii": 3,
            "wii controller": 3,
            "gamecube controllers": 3,
            "oem nintendo": 3,
            "silver platinum": 3,
            "cube": 3,
            "nintendo game": 3,
            "game cube": 3,
            "set 2": 3,
            "oem dol": 2,
            "various": 2
        }
    }
}