{
    "gdino": {
        "1": "4"
    },
    "gdino_readable": {
        "1": "Nintendo 2DS Console"
    },
    "gdino_improved": {
        "1": {
            "id": "svXJEQMnwuDfLPUHUUCi",
            "reference_name": "2DS",
            "itemtypes_name": null,
            "category": "Video Game Consoles",
            "model": "",
            "brand": "",
            "source": "vector_database",
            "contextual_text": "2DS | id: svXJEQMnwuDfLPUHUUCi | category: Video Game Consoles | Nintendo DS",
            "vector_index": 213,
            "embedding_norm": 1.0,
            "legacyId": null,
            "similarity_score": 0.8508256673812866
        }
    },
    "gdino_improved_readable": {
        "1": "2DS"
    },
    "gdino_similarity_scores": {
        "1": 0.8508
    },
    "gdino_classification_metadata": {
        "processed_date": "1757576414.8552215",
        "vector_db_version": "2.1",
        "model_used": "intfloat/multilingual-e5-base",
        "min_similarity_threshold": 0.3,
        "position_weighting_enabled": true,
        "position_classifier_config": {
            "decay_rate": 0.1,
            "top_k_boost": 8,
            "min_weight": 0.1,
            "hardware_boost": 1.5
        }
    },
    "gdino_tokens": {
        "1": [
            "nintendo",
            "2ds",
            "nintendo 2ds",
            "black",
            "console",
            "clear",
            "clear black",
            "2ds clear",
            "メルカリ",
            "red",
            "ニンテンドー2ds",
            "black console",
            "handheld",
            "2ds black",
            "3ds",
            "game",
            "com",
            "クリアブラック",
            "crimson",
            "crimson red",
            "2ds handheld",
            "handheld console",
            "game console",
            "stylus",
            "console stylus",
            "com nintendo",
            "本体",
            "ブラック",
            "2ds crimson",
            "nintendo 3ds",
            "used",
            "usb",
            "charging",
            "console used"
        ]
    }
}