{
  "gdino": {
    "1": "2"
  },
  "gdino_readable": {
    "1": "Nintendo DOL-003 GameCube Controller Tales of Symp"
  },
  "enhanced_classification": {
    "item_id": "Gynna5OzYWWE6y8WpgpO",
    "item_name": "GC Wavebird Con",
    "category": "Controllers & Attachments",
    "model": "",
    "validation_details": {
      "present_words": [
        "gc wavebird con"
      ],
      "key_words_coverage": 0.8386659622192383,
      "reason": "Vector database match with 0.839 similarity"
    }
  },
  "gdino_tokens": {
    "1": [
      "gamecube",
      "nintendo",
      "controller",
      "nintendo gamecube",
      "green",
      "gamecube controller",
      "tales",
      "symphonia",
      "symphonic",
      "tales symphonia",
      "wii",
      "symphonic green",
      "oem",
      "dol",
      "r",
      "game",
      "blue",
      "emerald",
      "controllers",
      "rare",
      "cube",
      "game cube",
      "r gamecube",
      "wired",
      "japan",
      "gamecube wii",
      "003",
      "gc",
      "dol 003",
      "pack",
      "gamecube tales",
      "custom",
      "com",
      "2",
      "ngc",
      "console",
      "wavebird",
      "tested",
      "emerald blue",
      "used",
      "controller tales",
      "symphonia symphonic",
      "enjoy"
    ]
  }
}