{
    "gdino": {
        "1": "20"
    },
    "gdino_readable": {
        "1": "Nintendo Switch Pro Controller"
    },
    "gdino_improved": {
        "1": {
            "id": "k40etST2II6zvZLnwAFz",
            "reference_name": "Wii U Gamepad",
            "itemtypes_name": null,
            "category": "Video Game Consoles",
            "model": "",
            "brand": "",
            "source": "vector_database",
            "contextual_text": "Wii U Gamepad | id: k40etST2II6zvZLnwAFz | category: Video Game Consoles | Nintendo Wii",
            "vector_index": 186,
            "embedding_norm": 1.0,
            "legacyId": null,
            "similarity_score": 0.8346798419952393
        }
    },
    "gdino_improved_readable": {
        "1": "Wii U Gamepad"
    },
    "gdino_similarity_scores": {
        "1": 0.8347
    },
    "gdino_classification_metadata": {
        "processed_date": "1757576414.8552215",
        "vector_db_version": "2.1",
        "model_used": "intfloat/multilingual-e5-base",
        "min_similarity_threshold": 0.3,
        "position_weighting_enabled": true,
        "position_classifier_config": {
            "decay_rate": 0.1,
            "top_k_boost": 8,
            "min_weight": 0.1,
            "hardware_boost": 1.5
        }
    },
    "gdino_tokens": {
        "1": [
            "smash",
            "controller",
            "nintendo",
            "bros",
            "smash bros",
            "wii",
            "u",
            "wii u",
            "gamecube"
        ]
    }
}