{
    "1": {
        "url": "https://storage.googleapis.com/strustore-dev.firebasestorage.app/gdino/3/d1190904638/mask_1.png",
        "bbox": [
            130,
            257,
            252,
            400
        ],
        "results": [
            {
                "title": "Nintendo Game Boy color with travel case and manual 4935228981649| eBay",
                "link": "https://www.ebay.com/itm/314190996698",
                "source": "www.ebay.com",
                "original_thumbnail": "https://i.ebayimg.com/images/g/KJYAAOSwWEdjTJhb/s-l400.jpg",
                "thumbnail": "https://encrypted-tbn1.gstatic.com/images?q=tbn:ANd9GcR9tssANM6_Kfz4pd9aOop3IpTLM2ixCPSuo0goGfYVM57eIUah",
                "tag": "$140",
                "in_stock": "In stock",
                "position": 1
            },
            {
                "title": "Nintendo Game Boy Color Pink Portable Game Console CGB-001 Japan W/Box , Manual | eBay",
                "link": "https://www.ebay.com/itm/204942631725",
                "source": "www.ebay.com",
                "original_thumbnail": "https://i.ebayimg.com/images/g/t6YAAOSwjPlmvgZe/s-l1200.jpg",
                "thumbnail": "https://encrypted-tbn1.gstatic.com/images?q=tbn:ANd9GcQbZm2R1v0qr2J3WP7F0NSQjEYAizu7B4b3w0gwXMMMT4yMmg-D",
                "position": 2
            },
            {
                "title": "Game Boy Color - Watermelon (Renewed) : Video Games - Amazon.com",
                "link": "https://www.amazon.com/Game-Boy-Color-Watermelon-Renewed/dp/B07QCPYWMC",
                "source": "www.amazon.com",
                "original_thumbnail": "https://m.media-amazon.com/images/I/41yAAsncosL._AC_SY200_QL15_.jpg",
                "thumbnail": "https://encrypted-tbn0.gstatic.com/images?q=tbn:ANd9GcT1klC4DUn6-3QsqJaPPMcjux3GICi68aFteHaTSVgjIYWSbhRl",
                "tag": "$87",
                "in_stock": "In stock",
                "position": 3
            },
            {
                "title": "Game Boy Color - Berry : Amazon.com.au: Video Games",
                "link": "https://www.amazon.com.au/Nintendo-0045496710774-Game-Boy-Color/dp/B0000296ZJ",
                "source": "www.amazon.com.au",
                "original_thumbnail": "https://m.media-amazon.com/images/I/61WmkowGR-L._AC_SY200_QL15_.jpg",
                "thumbnail": "https://encrypted-tbn3.gstatic.com/images?q=tbn:ANd9GcQNurC8z6FDqmJrIBbQ88xKM7dFNyv0CdjqsdDEIaVNTCyRshdX",
                "position": 4
            },
            {
                "title": "Nintendo Game Boy Color - Berry | GameStop",
                "link": "https://www.gamestop.com/consoles-hardware/retro-consoles/products/nintendo-game-boy-color-berry/10131398-10131401.html",
                "source": "www.gamestop.com",
                "original_thumbnail": "https://media.gamestop.com/i/gamestop/10131401/Nintendo-Game-Boy-Color-Berry",
                "thumbnail": "https://encrypted-tbn2.gstatic.com/images?q=tbn:ANd9GcRwDg-HjrmQy860jlnsaly2nuB4MfM6QT6dBpcuXojTdMlRi7gz",
                "position": 5
            },
            {
                "title": "Nintendo Game Boy Color Red Region Free Video Game Consoles for sale | eBay",
                "link": "https://www.ebay.com/b/Nintendo-Game-Boy-Color-Red-Region-Free-Video-Game-Consoles/139971/bn_109361811",
                "source": "www.ebay.com",
                "original_thumbnail": "https://i.ebayimg.com/images/g/2uQAAeSwY3VoeHKj/s-l225.jpg",
                "thumbnail": "https://encrypted-tbn3.gstatic.com/images?q=tbn:ANd9GcRk2z-LzyyTbrHZncUGDRXm3AzJEr4kWrWkVkJ7Gi5I2ZvTD_Zv",
                "position": 6
            },
            {
                "title": "Authentic GameBoy Color IPS Backlit Handheld GBC Systems \"Pick your color\" | eBay",
                "link": "https://www.ebay.com.my/itm/144237640710",
                "source": "www.ebay.com.my",
                "original_thumbnail": "https://i.ebayimg.com/00/s/MTYwMFgxNjAw/z/OWUAAOSw1cxlXEcp/$_12.JPG?set_id=880000500F",
                "thumbnail": "https://encrypted-tbn3.gstatic.com/images?q=tbn:ANd9GcTPEZQFHSmjjc5DjkULEp3Fl8ZPFXxE6BHsHtbP1806VbHsrNdF",
                "tag": "MYR 406",
                "in_stock": "In stock",
                "position": 7
            },
            {
                "title": "Gameboy Color Pink | eBay",
                "link": "https://www.ebay.com/shop/gameboy-color-pink?_nkw=gameboy+color+pink",
                "source": "www.ebay.com",
                "original_thumbnail": "https://i.ebayimg.com/images/g/1l0AAeSwXbBog4cJ/s-l300.jpg",
                "thumbnail": "https://encrypted-tbn0.gstatic.com/images?q=tbn:ANd9GcR8zO9cjvrZhXw8SI7gucQM2gPPqu-AkTMHUYNwd5222Xw85pzh",
                "position": 8
            },
            {
                "title": "Gameboy Color Red Console | eBay",
                "link": "https://www.ebay.com/shop/gameboy-color-red-console?_nkw=gameboy+color+red+console",
                "source": "www.ebay.com",
                "original_thumbnail": "https://i.ebayimg.com/images/g/ghkAAeSw2HtobUnB/s-l300.jpg",
                "thumbnail": "https://encrypted-tbn1.gstatic.com/images?q=tbn:ANd9GcQ6w7mDI1U7VU0ETnsWF31lCCEVvTvU33kAADqRFYE7VqhdkRwr",
                "position": 9
            },
            {
                "title": "Nintendo Game Boy Color Red Video Game Handheld Systems for sale | eBay",
                "link": "https://www.ebay.com/b/Nintendo-Game-Boy-Color-Red-Video-Game-Handheld-Systems/139971/bn_109358869",
                "source": "www.ebay.com",
                "original_thumbnail": "https://i.ebayimg.com/thumbs/images/g/J90AAeSwrF5oa4jb/s-l1200.jpg",
                "thumbnail": "https://encrypted-tbn1.gstatic.com/images?q=tbn:ANd9GcQzfXSdKkp7fW1b5ThMBw8dDPev1Ai7aAm2-fi9YU6Hmx4G_WU2",
                "position": 10
            },
            {
                "title": "Berry Gameboy Color | eBay",
                "link": "https://www.ebay.com/shop/berry-gameboy-color?_nkw=berry+gameboy+color",
                "source": "www.ebay.com",
                "original_thumbnail": "https://i.ebayimg.com/images/g/8qcAAeSw4epoijLw/s-l300.jpg",
                "thumbnail": "https://encrypted-tbn0.gstatic.com/images?q=tbn:ANd9GcTbuBevpc2ioUHQwZzmsNIPbmxS6K96gDLMCofvMY73K3LmW8QE",
                "position": 11
            },
            {
                "title": "Gameboy Ruby | eBay",
                "link": "https://www.ebay.com/shop/gameboy-ruby?_nkw=gameboy+ruby",
                "source": "www.ebay.com",
                "original_thumbnail": "https://i.ebayimg.com/images/g/bNsAAOSwmE5oXgTW/s-l300.jpg",
                "thumbnail": "https://encrypted-tbn1.gstatic.com/images?q=tbn:ANd9GcSgfR9pm8pKnHqRPgBDzr7shb8EBuec2H9XeTP40msUSkLxjvdO",
                "position": 12
            },
            {
                "title": "Nintendo Video Game Consoles Red VGA for sale | eBay",
                "link": "https://www.ebay.com/b/Nintendo-Video-Game-Consoles-Red-VGA/139971/bn_109357846",
                "source": "www.ebay.com",
                "original_thumbnail": "https://i.ebayimg.com/thumbs/images/g/cwEAAeSwlK5oWNu3/s-l1200.jpg",
                "thumbnail": "https://encrypted-tbn1.gstatic.com/images?q=tbn:ANd9GcQVMc8WMg_M9oDhbssutkuG5DaMbDtlugG_GU9XVTXS6tdZ1kYe",
                "position": 13
            },
            {
                "title": "Nintendo Game Boy Color in Berry - FOR PARTS for Sale in Brooklyn, NY - OfferUp",
                "link": "https://offerup.com/item/detail/141ff4b5-a56c-37a9-9099-1e40dff17cbd",
                "source": "offerup.com",
                "original_thumbnail": "https://images.offerup.com/iC2RZOeHjQgytxk0bqVXI429SIo=/355x250/b1d4/b1d4fec0c6ed4ee28ef1e03a6d8529ee.jpg",
                "thumbnail": "https://encrypted-tbn0.gstatic.com/images?q=tbn:ANd9GcTrPkga2AtMMSgPPrnlr8lOI7m6XPV1ohj5mfD4Y1hkFe4-w6J2",
                "position": 14
            },
            {
                "title": "Nintendo Game Boy Color Pink Video Game Handheld Systems for sale | eBay",
                "link": "https://www.ebay.com/b/Nintendo-Game-Boy-Color-Pink-Video-Game-Handheld-Systems/139971/bn_109357845",
                "source": "www.ebay.com",
                "original_thumbnail": "https://i.ebayimg.com/thumbs/images/g/GgAAAOSwZZxhAx3d/s-l1200.jpg",
                "thumbnail": "https://encrypted-tbn1.gstatic.com/images?q=tbn:ANd9GcShqFBgRUEWU6mUsXJh9HArFxy0Y-AEuS2J862xjBt-ERI3Yfx2",
                "position": 15
            },
            {
                "title": "Nintendo Color | eBay",
                "link": "https://www.ebay.com/shop/nintendo-color?_nkw=nintendo+color",
                "source": "www.ebay.com",
                "original_thumbnail": "https://i.ebayimg.com/images/g/TlYAAeSw4x5oiY5z/s-l300.jpg",
                "thumbnail": "https://encrypted-tbn2.gstatic.com/images?q=tbn:ANd9GcT20noN4lap2UdVCPjoUQg7GQVyFjk1-2MNb0AyWFhzUdkX_myH",
                "position": 16
            },
            {
                "title": "Original Nintendo Game Boy Color in Berry | Mercari",
                "link": "https://www.mercari.com/us/item/m85259848644/",
                "source": "www.mercari.com",
                "original_thumbnail": "https://u-mercari-images.mercdn.net/thumb/photos/m32976840979_1.jpg?width=2560&quality=75&_=1749239671",
                "thumbnail": "https://encrypted-tbn3.gstatic.com/images?q=tbn:ANd9GcSmEfEdwezCNYewoG77or2rT2rh8XMGk7F7lY38hyOoRmncHLEz",
                "tag": "$86",
                "in_stock": "In stock",
                "position": 17
            },
            {
                "title": "Red VGA Video Game Handheld Systems for sale | eBay",
                "link": "https://www.ebay.com/b/Red-VGA-Video-Game-Handheld-Systems/139971/bn_109360913",
                "source": "www.ebay.com",
                "original_thumbnail": "https://i.ebayimg.com/images/g/5HkAAeSwfAtoWNu3/s-l225.jpg",
                "thumbnail": "https://encrypted-tbn1.gstatic.com/images?q=tbn:ANd9GcSR6e-eHCe3pQ3KFoholLbK8SCmXY2BGZvYH_D-6KPmutAYSQ1O",
                "position": 18
            },
            {
                "title": "Gameboy Red | eBay",
                "link": "https://www.ebay.com/shop/gameboy-red?_nkw=gameboy+red",
                "source": "www.ebay.com",
                "original_thumbnail": "https://i.ebayimg.com/images/g/NNcAAOSwd31oUyUk/s-l300.jpg",
                "thumbnail": "https://encrypted-tbn2.gstatic.com/images?q=tbn:ANd9GcQyGonOgwOcOfaO-G_BSZPGPycDlYBatllx_JE5pCceOtkZp8Vv",
                "position": 19
            },
            {
                "title": "Nintendo Game Boy GB Color Console RED CGB-001 Tested | eBay",
                "link": "https://www.ebay.com/itm/396600724378",
                "source": "www.ebay.com",
                "original_thumbnail": "https://i.ebayimg.com/images/g/VaYAAOSwti5oIexf/s-l1200.jpg",
                "thumbnail": "https://encrypted-tbn3.gstatic.com/images?q=tbn:ANd9GcTLQjVwzGBz8mK9cl-FiuLlUsqEpxMMcroYG27O-DPQXtqnwzBA",
                "position": 20
            },
            {
                "title": "Small Osaka Warehouse | eBay Stores",
                "link": "https://www.ebay.com/str/smallosakawarehouse",
                "source": "www.ebay.com",
                "original_thumbnail": "https://i.ebayimg.com/images/g/wskAAOSwsOVmdnEq/s-l300.jpg",
                "thumbnail": "https://encrypted-tbn3.gstatic.com/images?q=tbn:ANd9GcQd_V3-_BPhxO8YvgCxCTeHPjgAnNnrPZyvKaZAhl7RFCMJlTQX",
                "position": 21
            },
            {
                "title": "Nintendo Game Boy Color CGB-001 Tested Workimg Color variations JpGames GBC | eBay",
                "link": "https://www.ebay.com/itm/386829096819",
                "source": "www.ebay.com",
                "original_thumbnail": "https://i.ebayimg.com/images/g/DckAAOSwKrFl8ZPh/s-l1200.jpg",
                "thumbnail": "https://encrypted-tbn0.gstatic.com/images?q=tbn:ANd9GcRPo7CIbBSt5Kix68voSquTWahfPz6hC5PP_7wGs-ASB12lrDGe",
                "tag": "$95",
                "in_stock": "In stock",
                "position": 22
            },
            {
                "title": "The Addams Family Pugsley's Scavenger Hunt Gig ITA Nintendo Game Boy | eBay",
                "link": "https://www.ebay.com/itm/226664295906",
                "source": "www.ebay.com",
                "original_thumbnail": "https://i.ebayimg.com/images/g/0SAAAOSwn-djq0o9/s-l1200.jpg",
                "thumbnail": "https://encrypted-tbn3.gstatic.com/images?q=tbn:ANd9GcRvRArE_tdTTD8IVSQEr_WwnZNBJhRjU8WlBr0GD-yUad5AiKuU",
                "tag": "$52",
                "in_stock": "In stock",
                "position": 23
            },
            {
                "title": "Game Boy Color Body Red Operation Confirmed With Cassette | eBay",
                "link": "https://www.ebay.com/itm/306001771200",
                "source": "www.ebay.com",
                "original_thumbnail": "https://i.ebayimg.com/images/g/6nwAAOSwZz9nbr4u/s-l400.jpg",
                "thumbnail": "https://encrypted-tbn1.gstatic.com/images?q=tbn:ANd9GcR1shTV6mRjvzpeiI4W60_-iRYlxeWbdU-oIw8w7tEQ7DkZH1kC",
                "position": 24
            },
            {
                "title": "Wario Land Nintendo Game Boy GBC GBA GBA SP NEW SAVE BATTERY #92 | eBay",
                "link": "https://www.ebay.com/itm/116396316778",
                "source": "www.ebay.com",
                "original_thumbnail": "https://i.ebayimg.com/00/s/MTIwMFgxNjAw/z/XfIAAOSwqzFnZf6o/$_1.JPG?set_id=2",
                "thumbnail": "https://encrypted-tbn1.gstatic.com/images?q=tbn:ANd9GcQLl5oQWxZ02rvuNzbCCkHqkucbeuv8R71OubcnNcijgfJWV_eS",
                "position": 25
            },
            {
                "title": "Nintendo Game boy Color Console Red Region free CGB-001 - pre owned - | eBay",
                "link": "https://www.ebay.com/itm/176723781265",
                "source": "www.ebay.com",
                "original_thumbnail": "https://i.ebayimg.com/images/g/MyMAAOSwg~FnVEQ6/s-l1200.jpg",
                "thumbnail": "https://encrypted-tbn0.gstatic.com/images?q=tbn:ANd9GcSz0rfKt9wizso0LdNBy3_bcA8R_Xuw7YEavHGxoEjUxvfuTwt7",
                "tag": "$75",
                "in_stock": "In stock",
                "position": 26
            },
            {
                "title": "Nintendo Game Boy Color GBC Motherboard Board FOR PARTS (READ) #A | eBay",
                "link": "https://www.ebay.com/itm/204353675552",
                "source": "www.ebay.com",
                "original_thumbnail": "https://i.ebayimg.com/00/s/MTYwMFgxMjAw/z/hVgAAOSwyxtld8Mi/$_12.JPG?set_id=880000500F",
                "thumbnail": "https://encrypted-tbn1.gstatic.com/images?q=tbn:ANd9GcSDlJesjnZb0uuBfMioGsU8dhLSJus7yEq0nVbouc9RrMXloufd",
                "tag": "$45",
                "in_stock": "In stock",
                "position": 27
            },
            {
                "title": "Authentic GameBoy Color IPS Backlit Handheld GBC Systems \"Pick your color\" | eBay",
                "link": "https://www.ebay.com/itm/144237640710",
                "source": "www.ebay.com",
                "original_thumbnail": "https://i.ebayimg.com/00/s/MTYwMFg3NDA=/z/7G4AAOSwghJl2Wp-/$_12.JPG?set_id=880000500F",
                "thumbnail": "https://encrypted-tbn2.gstatic.com/images?q=tbn:ANd9GcTNWsdGKyzpKmH0nNd-anLlso7ehIxGcc-dNRQWLbABPseHIbEq",
                "tag": "$95",
                "in_stock": "In stock",
                "position": 28
            },
            {
                "title": "Is this gameboy color shell original or fake? I bought this yesterday, but i was thinking the original color was magenta: this is pure red. Can you help me? : r/Gameboy",
                "link": "https://www.reddit.com/r/Gameboy/comments/erbjfl/is_this_gameboy_color_shell_original_or_fake_i/",
                "source": "www.reddit.com",
                "original_thumbnail": "https://i.redd.it/grgobgiouwb41.jpg",
                "thumbnail": "https://encrypted-tbn3.gstatic.com/images?q=tbn:ANd9GcThFwNnxQENqnOuBQppkNmf0_CZobndY9VWMWthbtjs6u9V0mY7",
                "position": 29
            },
            {
                "title": "Atlantis Lost Empire (Nintendo Gameboy Color GBC) Cart Only Game Boy 785138320687| eBay",
                "link": "https://www.ebay.com/itm/156251303506",
                "source": "www.ebay.com",
                "original_thumbnail": "https://i.ebayimg.com/images/g/BcEAAOSwS6NmZ9s7/s-l1200.jpg",
                "thumbnail": "https://encrypted-tbn3.gstatic.com/images?q=tbn:ANd9GcSyfyiTyXvJNLCuZVnsBJrXbgzs8iXLf8qpuLwxwzSCUX_2eke0",
                "tag": "$5",
                "in_stock": "In stock",
                "position": 30
            },
            {
                "title": "Nintendo Cgb-S-Ra Gameboy Color | eBay",
                "link": "https://www.ebay.com/itm/356555185403",
                "source": "www.ebay.com",
                "original_thumbnail": "https://i.ebayimg.com/images/g/k5MAAeSwEIxnqm3A/s-l400.jpg",
                "thumbnail": "https://encrypted-tbn3.gstatic.com/images?q=tbn:ANd9GcTAGkO3hiQ6Km_dInFnNpgFuqE-kEVf7smL256FQVKDiWqLnt_s",
                "tag": "$252",
                "in_stock": "In stock",
                "position": 31
            },
            {
                "title": "GameBoy Color Red Console CPU-02 CGB-001 w/pokemon crystal tested from Japan | eBay",
                "link": "https://www.ebay.com/itm/204998634441",
                "source": "www.ebay.com",
                "original_thumbnail": "https://i.ebayimg.com/images/g/U2sAAOSwdrZm6ipN/s-l400.jpg",
                "thumbnail": "https://encrypted-tbn3.gstatic.com/images?q=tbn:ANd9GcSCWTh4YN8-zPpvY9MDZVv5Pys1aPNhExwpIRw3nbNE6XmGqxMJ",
                "position": 32
            },
            {
                "title": "Nintendo Cgb-001 | eBay",
                "link": "https://www.ebay.com/itm/356583514743",
                "source": "www.ebay.com",
                "original_thumbnail": "https://i.ebayimg.com/images/g/TKMAAeSwdDBns6hf/s-l1200.jpg",
                "thumbnail": "https://encrypted-tbn1.gstatic.com/images?q=tbn:ANd9GcQqHy9Cdbq_U4Hl69BgiTNwCSPt08jouILpgXut6BOjzbEcMPle",
                "tag": "$170",
                "in_stock": "In stock",
                "position": 33
            },
            {
                "title": "NINTENDO GAME BOY COLOR BERRY RED BOXED MATCH SERIAL | eBay",
                "link": "https://www.ebay.com/itm/356581531282",
                "source": "www.ebay.com",
                "original_thumbnail": "https://i.ebayimg.com/images/g/dyEAAOSwWjxnsucg/s-l1200.jpg",
                "thumbnail": "https://encrypted-tbn2.gstatic.com/images?q=tbn:ANd9GcQJoxcLn6R9jiKbFblWmfUYyFiKEXp2EXe7eMRn0ycyAfMbjdKW",
                "position": 34
            },
            {
                "title": "Penguin Boy DMG- PNJ Nintendo Game Boy | eBay",
                "link": "https://www.ebay.com/itm/226664296361",
                "source": "www.ebay.com",
                "original_thumbnail": "https://i.ebayimg.com/images/g/aNIAAOSwtdFjq1CA/s-l1200.jpg",
                "thumbnail": "https://encrypted-tbn2.gstatic.com/images?q=tbn:ANd9GcQYLGB1pCBAaOEHH6L_3LbqGwcHil-Zwdr0P_CXuYLu5EohQ5dj",
                "tag": "$30",
                "in_stock": "In stock",
                "position": 35
            },
            {
                "title": "Quarth - Nintendo Gameboy, GB - Testing & Working 83717145042| eBay",
                "link": "https://www.ebay.com/itm/276521197787",
                "source": "www.ebay.com",
                "original_thumbnail": "https://i.ebayimg.com/images/g/en8AAOSwc7Nmd6TO/s-l1200.png",
                "thumbnail": "https://encrypted-tbn0.gstatic.com/images?q=tbn:ANd9GcTYVwBeCrGKCT7IWsc0_RbwC6w6iZpnRgeYoJtVK8qSzhGtljf5",
                "tag": "$12",
                "in_stock": "In stock",
                "position": 36
            },
            {
                "title": "L3346 Nintendo Gameboy Color console Red Japan GBC x | eBay",
                "link": "https://www.ebay.com/itm/226467511712",
                "source": "www.ebay.com",
                "original_thumbnail": "https://i.ebayimg.com/00/s/MTIwMFgxNjAw/z/YGsAAOSwx7dnRbBB/$_57.JPG?set_id=880000500F",
                "thumbnail": "https://encrypted-tbn3.gstatic.com/images?q=tbn:ANd9GcSNEa2oyCDqXs5l-XgnD9bYG1_w3Rkx0UiulC73bv60_Mt4wdwl",
                "tag": "$50",
                "in_stock": "In stock",
                "position": 37
            },
            {
                "title": "Consola Game Boy Color Original Berry Original | MercadoLibre",
                "link": "https://articulo.mercadolibre.com.mx/MLM-2785827778-consola-game-boy-color-original-berry-original-_JM",
                "source": "articulo.mercadolibre.com.mx",
                "original_thumbnail": "https://http2.mlstatic.com/D_NQ_NP_896635-MLM73648558918_012024-O-consola-game-boy-color-original-berry-original.webp",
                "thumbnail": "https://encrypted-tbn0.gstatic.com/images?q=tbn:ANd9GcS-Uauisc1th_MCrDSRYdY3gWjoZZw_-q9cuMAhSJ9rE_roDBB_",
                "tag": "MX$1,299",
                "in_stock": "In stock",
                "position": 38
            },
            {
                "title": "Nintendo Game Boy Color Red Used Item | eBay",
                "link": "https://www.ebay.com/itm/315691047578",
                "source": "www.ebay.com",
                "original_thumbnail": "https://i.ebayimg.com/images/g/u6IAAOSwOuRmxwiu/s-l400.jpg",
                "thumbnail": "https://encrypted-tbn3.gstatic.com/images?q=tbn:ANd9GcTY-qzq8kxx3Fwl2EUnKraleLKk7uzP1Vobxr2UuCxt3JaRf9ib",
                "tag": "$191",
                "in_stock": "In stock",
                "position": 39
            },
            {
                "title": "Berry Red GameBoy Color Authentic Nintendo GBC Handheld Console MINT CONDITION! | eBay",
                "link": "https://www.ebay.com/itm/385586306446?_ul=CR",
                "source": "www.ebay.com",
                "original_thumbnail": "https://i.ebayimg.com/00/s/MTYwMFgxNjAw/z/jkgAAOSwt4lnPAiZ/$_57.PNG?set_id=880000500F",
                "thumbnail": "https://encrypted-tbn3.gstatic.com/images?q=tbn:ANd9GcT17XIS-oUpNSHviGZeJyKOlTpjO7woGqnCy_sCl6ejhO0GePe0",
                "tag": "$110",
                "in_stock": "In stock",
                "position": 40
            },
            {
                "title": "Gameboy Color Stand Display Accessory Holder Gift Metallic Customize | eBay",
                "link": "https://www.ebay.com/itm/205032199441",
                "source": "www.ebay.com",
                "original_thumbnail": "https://i.ebayimg.com/images/g/7KEAAOSwdFVnBKt8/s-l1200.jpg",
                "thumbnail": "https://encrypted-tbn1.gstatic.com/images?q=tbn:ANd9GcRwnxcJCZTmBd3GUYJek4aka8Rx68eV6qmSUDK0UgWLbbWGwRmh",
                "tag": "$14",
                "in_stock": "In stock",
                "position": 41
            },
            {
                "title": "game boy color · Whatnot: Shop, Sell, Connect",
                "link": "https://www.whatnot.com/listing/TGlzdGluZ05vZGU6NTAxMTczMTkx",
                "source": "www.whatnot.com",
                "original_thumbnail": "https://images.whatnot.com/fit-in/3840x0/filters:format(webp)/listings/0-0088bfe3-adb2-479e-9c21-46c34df927ae-86c58ba7-d9b1-4159-9d1e-cde4aba64547.jpeg",
                "thumbnail": "https://encrypted-tbn3.gstatic.com/images?q=tbn:ANd9GcRjtoSOh_Gn99M4u321KuBVux6ScH_nZBn4bJV8gmcPAH8yYOVR",
                "tag": "$54",
                "in_stock": "In stock",
                "position": 42
            },
            {
                "title": "Nintendo Pink GameBoy Color (CGB-001) & PowerPuff Girls Battle Him WORKS! *READ | eBay",
                "link": "https://www.ebay.com/itm/266546741418",
                "source": "www.ebay.com",
                "original_thumbnail": "https://i.ebayimg.com/images/g/MyoAAOSwMOxlbAwj/s-l1200.jpg",
                "thumbnail": "https://encrypted-tbn1.gstatic.com/images?q=tbn:ANd9GcRTajQwRkNfhhJMK0yPP7u4HIPEGqwEyoHXAJjO8EBx9eq5N_WF",
                "tag": "$80",
                "in_stock": "In stock",
                "position": 43
            },
            {
                "title": "Game Boy Color Glass Screen for TFT LCD Black & White - HHL",
                "link": "https://handheldlegend.com/products/game-boy-color-glass-screen-tft",
                "source": "handheldlegend.com",
                "original_thumbnail": "https://judgeme.imgix.net/hand-held-legend/1733298251__img_6030__original.jpeg?auto=format&w=160",
                "thumbnail": "https://encrypted-tbn1.gstatic.com/images?q=tbn:ANd9GcSDxMcylenHs6oD60iIXnyasKVXHLV15JofaFhGTnwYYr35hWbZ",
                "tag": "$3",
                "in_stock": "In stock",
                "position": 44
            },
            {
                "title": "Nintendo Game Boy Color CGB-001 - Berry Red Broken Battery Cover",
                "link": "https://www.clinicabeautylounge.com/shopdetail/7529920/",
                "source": "www.clinicabeautylounge.com",
                "original_thumbnail": "https://u-mercari-images.mercdn.net/photos/m29173672204_4.jpg",
                "thumbnail": "https://encrypted-tbn0.gstatic.com/images?q=tbn:ANd9GcQ5-0y5yF12FcSq7RoV3Y0pjHseRrJmEpCCrfrQR3XrJpGr14yy",
                "position": 45
            },
            {
                "title": "Nintendo Game Boy Color Berry Pink Console Lot w 4 Games Nuby Accessories Tested | eBay",
                "link": "https://www.ebay.com/itm/126012153720",
                "source": "www.ebay.com",
                "original_thumbnail": "https://i.ebayimg.com/images/g/jloAAOSwvopjh66q/s-l1200.jpg",
                "thumbnail": "https://encrypted-tbn2.gstatic.com/images?q=tbn:ANd9GcRSirltaKtF378h1Tqi8cgAyPXxoxWwCt7Usn6nRcePJazWUr5t",
                "tag": "$200",
                "in_stock": "In stock",
                "position": 46
            },
            {
                "title": "Nintendo Game Boy Color GBC System Backlight Backlit Brighter TFT Berry | eBay",
                "link": "https://www.ebay.com/itm/193184389451",
                "source": "www.ebay.com",
                "original_thumbnail": "https://i.ebayimg.com/images/g/2~oAAOSwt-Bduf2B/s-l400.jpg",
                "thumbnail": "https://encrypted-tbn1.gstatic.com/images?q=tbn:ANd9GcS2nw1Jfvlk8AvCYOJRRs4VNnQQchjKC4UdGuezTJWf11afctJu",
                "tag": "$160",
                "in_stock": "In stock",
                "position": 47
            },
            {
                "title": "Nintendo Game Boy Color GBC Q5 IPS Backlight Backlit KIT Berry Shell Button | eBay",
                "link": "https://www.ebay.com/itm/203675939582",
                "source": "www.ebay.com",
                "original_thumbnail": "https://i.ebayimg.com/images/g/3rQAAOSwLAxhew3V/s-l400.jpg",
                "thumbnail": "https://encrypted-tbn2.gstatic.com/images?q=tbn:ANd9GcSVxjbP-AQy1rZT5qZyZ1CxwcGhyRdmWrhvVAlvTQ77Gtbs4PuM",
                "tag": "$95",
                "in_stock": "In stock",
                "position": 48
            },
            {
                "title": "Nintendo Game Boy Color Red Hand Held Console - Baxtros",
                "link": "https://baxtros.co.uk/product/nintendo-gameboy-color-red-console/",
                "source": "baxtros.co.uk",
                "original_thumbnail": "https://baxtros.co.uk/wp-content/uploads/2016/10/DSC_0868-150x150.jpg",
                "thumbnail": "https://encrypted-tbn1.gstatic.com/images?q=tbn:ANd9GcRRI9WA4Zs7uVf9ttqAUdZa80sCGO3oMqn82HVI3nTtXbx3NnBv",
                "position": 49
            },
            {
                "title": "Nintendo Game Boy Color - Red - Unboxed | eBay UK",
                "link": "https://www.ebay.co.uk/itm/177085023257",
                "source": "www.ebay.co.uk",
                "original_thumbnail": "https://i.ebayimg.com/images/g/nVsAAOSwbyFoIINH/s-l400.png",
                "thumbnail": "https://encrypted-tbn0.gstatic.com/images?q=tbn:ANd9GcRtAN2p0zuo__OfROKlC46JKEThiY2BzxDnbCiWIHrfKpa5Jjft",
                "position": 50
            },
            {
                "title": "My gameboy color light : r/Gameboy",
                "link": "https://www.reddit.com/r/Gameboy/comments/195k09m/my_gameboy_color_light/",
                "source": "www.reddit.com",
                "original_thumbnail": "https://preview.redd.it/my-gameboy-color-light-v0-po7enxslb6cc1.jpeg?width=640&crop=smart&auto=webp&s=825a0d68bdb5158592be24ad1fb92b723b3541f1",
                "thumbnail": "https://encrypted-tbn2.gstatic.com/images?q=tbn:ANd9GcSoiyo2uIxqfBqx5P3Rfzgnaq04cuKSexKFnmluRlSp1Fje0hM8",
                "position": 51
            },
            {
                "title": "GBC Retropixel OSD IPS kit, backlight stopped working : r/Gameboy",
                "link": "https://www.reddit.com/r/Gameboy/comments/mufv61/gbc_retropixel_osd_ips_kit_backlight_stopped/",
                "source": "www.reddit.com",
                "original_thumbnail": "https://i.redd.it/vm1jmkkig8u61.jpg",
                "thumbnail": "https://encrypted-tbn1.gstatic.com/images?q=tbn:ANd9GcQu_GrqPv1z_7Sbl-xxIxXiWp1SZXDQ_xN6TNEu5AM7aQXi7jyZ",
                "position": 52
            },
            {
                "title": "Nintendo Gameboy Colour Pink, working, plus power adapter & cables & a game | eBay UK",
                "link": "https://www.ebay.co.uk/itm/146626678277",
                "source": "www.ebay.co.uk",
                "original_thumbnail": "https://i.ebayimg.com/images/g/fGsAAeSwl3loQGku/s-l400.jpg",
                "thumbnail": "https://encrypted-tbn3.gstatic.com/images?q=tbn:ANd9GcTv4vCasU5C6aiH2aFCVbOVwnrtsiWRNK87PtIug6jFp1gLfaWQ",
                "position": 53
            },
            {
                "title": "Nintendo Gameboy Color Red + Game",
                "link": "https://vintomatic.com/store/retro-gaming/nintendo-gameboy-color-red-game/",
                "source": "vintomatic.com",
                "original_thumbnail": "https://vintomatic.com/wp-content/uploads/2021/06/20210601_204032-rotated.jpg",
                "thumbnail": "https://encrypted-tbn2.gstatic.com/images?q=tbn:ANd9GcRn0A992Yc2SmGH0ePhXjql9Mjlls0DqDVCD6nv6kaqMuZVByMz",
                "position": 54
            },
            {
                "title": "Nintendo Game Boy Color GBC System Berry Red Hand Held Console Grade A | eBay UK",
                "link": "https://www.ebay.co.uk/itm/201941112716",
                "source": "www.ebay.co.uk",
                "original_thumbnail": "https://i.ebayimg.com/images/g/rfsAAOSwC-JaqmIT/s-l400.jpg",
                "thumbnail": "https://encrypted-tbn3.gstatic.com/images?q=tbn:ANd9GcRdTBOyXDXkOUVcjnra-xaDAC-3of5o3vLzyggEql9u-GhxgHwp",
                "position": 55
            },
            {
                "title": "Gameboy color : r/gameverifying",
                "link": "https://www.reddit.com/r/gameverifying/comments/1abt7se/gameboy_color/",
                "source": "www.reddit.com",
                "original_thumbnail": "https://preview.redd.it/gameboy-color-v0-lf8f4j4gpuec1.jpg?width=108&crop=smart&auto=webp&s=c66e3478f6771c74d0077942ece8c9c161f7b5a5",
                "thumbnail": "https://encrypted-tbn1.gstatic.com/images?q=tbn:ANd9GcTGh7YMGRm74vHdwHnZ6-rWvej8byFtyoAcVrR_tTTS5QgBa6Gs",
                "position": 56
            },
            {
                "title": "Gameboy color issue : r/Gameboy",
                "link": "https://www.reddit.com/r/Gameboy/comments/1l2wnv0/gameboy_color_issue/",
                "source": "www.reddit.com",
                "original_thumbnail": "https://preview.redd.it/gameboy-color-issue-v0-5n7sa28u8u4f1.jpg?width=640&crop=smart&auto=webp&s=c3fc97695d555ab2f5ffe1108957379034f94224",
                "thumbnail": "https://encrypted-tbn0.gstatic.com/images?q=tbn:ANd9GcSUptGhqTYXSQHjYdkcnu1TzCiE7iCRh-3pRGhqQMXg1-9UPS0n",
                "position": 57
            },
            {
                "title": "Gameboy Color Volume Wheel Guard por iNEADthat | Descargar modelo STL gratuito | Printables.com",
                "link": "https://www.printables.com/es/model/471063-gameboy-color-volume-wheel-guard",
                "source": "www.printables.com",
                "original_thumbnail": "https://media.printables.com/media/prints/471063/images/3858898_8e9d3dcc-3c8c-42c2-98c0-6b2904bd914f/thumbs/cover/320x240/jpg/017cc4f35ab832e725cd29ad80414cbc4f218847ca.webp",
                "thumbnail": "https://encrypted-tbn1.gstatic.com/images?q=tbn:ANd9GcRPWITa8jTMTRzfCm5ZN99MLZJs8rQA13oP4WRmeaezYdpt3e1J",
                "position": 58
            },
            {
                "title": "Nintendo Game Boy Color CGB-001 - Berry Red Broken Battery Cover Consoles",
                "link": "https://indiainformatics.net/67014842.htm",
                "source": "indiainformatics.net",
                "original_thumbnail": "https://u-mercari-images.mercdn.net/photos/m29173672204_5.jpg",
                "thumbnail": "https://encrypted-tbn1.gstatic.com/images?q=tbn:ANd9GcQdJYq0-49Q1xjA2DoAmaT3cJ9STc3RAdaMQRzWv8tbzERaqp6m",
                "position": 59
            }
        ],
        "tokens": [
            "color",
            "game",
            "nintendo",
            "boy",
            "game boy",
            "boy color",
            "gameboy",
            "nintendo game",
            "red",
            "gameboy color",
            "berry",
            "gbc",
            "console",
            "cgb",
            "001",
            "cgb 001",
            "color red",
            "video",
            "pink",
            "color berry",
            "handheld",
            "video game",
            "systems",
            "original",
            "color gbc",
            "r",
            "nintendo gameboy",
            "berry red",
            "ips",
            "backlit",
            "tested",
            "color cgb",
            "r gameboy",
            "japan",
            "w",
            "color pink",
            "games",
            "com",
            "consoles",
            "authentic",
            "game handheld",
            "handheld systems",
            "color console",
            "console red"
        ]
    },
    "2": {
        "url": "https://storage.googleapis.com/strustore-dev.firebasestorage.app/gdino/3/d1190904638/mask_2.png",
        "bbox": [
            244,
            261,
            353,
            407
        ],
        "results": [
            {
                "title": "Premium Glass Replacement Lens for Game Boy Color | eBay",
                "link": "https://www.ebay.com/itm/394047256614",
                "source": "www.ebay.com",
                "original_thumbnail": "https://i.ebayimg.com/images/g/iQ0AAOSwOPFiaFVY/s-l400.jpg",
                "thumbnail": "https://encrypted-tbn0.gstatic.com/images?q=tbn:ANd9GcTc7WszOfQtSf8aeP4rXOUHsdeLZ6eyMYuO9kO7LK2jd9atFTVL",
                "position": 1
            },
            {
                "title": "OSTENT Full Housing Shell Case Cover Replacement for Nintendo GBC Gameboy Color Console - Color Yellow : Amazon.sg: Video Games",
                "link": "https://www.amazon.sg/OSTENT-Housing-Replacement-Nintendo-Gameboy/dp/B07D3S558W",
                "source": "www.amazon.sg",
                "original_thumbnail": "https://m.media-amazon.com/images/I/51JC8AUi6gL._UF350,350_QL80_.jpg",
                "thumbnail": "https://encrypted-tbn0.gstatic.com/images?q=tbn:ANd9GcTvvwtDLDbgu3aztRUhdBD3cKOK39wWnZQgwf_WVEA8lSYaWfZo",
                "tag": "SGD 8",
                "in_stock": "In stock",
                "position": 2
            },
            {
                "title": "ゲームボーイ カラー (イエロー)【メーカー生産終了】 : Amazon.de: Games",
                "link": "https://www.amazon.de/ゲームボーイ-カラー-イエロー-【メーカー生産終了】/dp/B000031KAU",
                "source": "www.amazon.de",
                "original_thumbnail": "https://m.media-amazon.com/images/I/41N7YqCWRwL._AC_SY200_QL15_.jpg",
                "thumbnail": "https://encrypted-tbn2.gstatic.com/images?q=tbn:ANd9GcTdWcHBWthqjgiUVowDi8oNYvNM-iZ4it0Qc8ywHWvvo70-a9yH",
                "position": 3
            },
            {
                "title": "Game Boy Color - Dandelion (Renewed) : 電動遊戲 - Amazon.com",
                "link": "https://www.amazon.com/-/zh_TW/Game-Boy-Color-Dandelion-Renewed/dp/B07KPPQG1W",
                "source": "www.amazon.com",
                "original_thumbnail": "https://m.media-amazon.com/images/I/81RB3lbaJXL._UF1000,1000_QL80_.jpg",
                "thumbnail": "https://encrypted-tbn2.gstatic.com/images?q=tbn:ANd9GcQNwGWulClv96b-75m7VnTlOWwuv3msItzMlslEQbtP3IPuHxF7",
                "tag": "$95",
                "in_stock": "In stock",
                "position": 4
            },
            {
                "title": "Game Boy Color Yellow & Game Boy Advance Orange Box with Instructions | eBay",
                "link": "https://www.ebay.com/itm/356596647393",
                "source": "www.ebay.com",
                "original_thumbnail": "https://i.ebayimg.com/images/g/tOYAAOSwie5nuKn0/s-l400.jpg",
                "thumbnail": "https://encrypted-tbn3.gstatic.com/images?q=tbn:ANd9GcQksv1H2YlQ0i1fK8Su0bqcoTWKp_5VUlposH4XXLlIlOyPqd5_",
                "tag": "$140",
                "in_stock": "In stock",
                "position": 5
            },
            {
                "title": "Nintendo Game Boy Dandelion Yellow Handheld Game System 45496710798 | eBay UK",
                "link": "https://www.ebay.co.uk/itm/186907795196",
                "source": "www.ebay.co.uk",
                "original_thumbnail": "https://i.ebayimg.com/images/g/3MIAAOSwD59nkPRk/s-l400.jpg",
                "thumbnail": "https://encrypted-tbn3.gstatic.com/images?q=tbn:ANd9GcSLPEnpauDjbNNq_WgCU38DmlcuH49Wxuf3eWjbIRuydBVCjYUz",
                "position": 6
            },
            {
                "title": "SKU GA02 F3 | Game Boy Color Nin Yellow GBC Used - Etsy India",
                "link": "https://www.etsy.com/in-en/listing/1738226476/sku-ga02-f3-game-boy-color-nin-yellow",
                "source": "www.etsy.com",
                "original_thumbnail": "https://i.etsystatic.com/28416524/r/il/12aa0f/6082300784/il_300x300.6082300784_pu5p.jpg",
                "thumbnail": "https://encrypted-tbn3.gstatic.com/images?q=tbn:ANd9GcQI8dz7Pwhdeg70ux9Pr129JksW9kcn9deE0CVv1XSMJ-hxESlt",
                "position": 7
            },
            {
                "title": "Buy 2250 in 1 Nintendo Game Cartridge Gameboy Color English 16 Bit Save Progress Online in India - Etsy",
                "link": "https://www.etsy.com/in-en/listing/1205438354/2750-in-1-nintendo-game-cartridge?ref=ap-listing",
                "source": "www.etsy.com",
                "original_thumbnail": "https://i.etsystatic.com/32446531/r/il/a15917/3872560241/il_fullxfull.3872560241_8n85.jpg",
                "thumbnail": "https://encrypted-tbn1.gstatic.com/images?q=tbn:ANd9GcTd7fn0yGKfH_OmE_3v5CnL65xR4aja3A0pdbBJfqW4I1JNUOpS",
                "position": 8
            },
            {
                "title": "Nintendo Gameboy Color Console Yellow Cib Tested | eBay",
                "link": "https://www.ebay.ca/itm/306092606604",
                "source": "www.ebay.ca",
                "original_thumbnail": "https://i.ebayimg.com/thumbs/images/g/fkoAAOSwd7Zno8TY/s-l1200.jpg",
                "thumbnail": "https://encrypted-tbn0.gstatic.com/images?q=tbn:ANd9GcQLiK7ngCuPP_xRXWVCB9KmbrCZwTRVEq-5LXoJqg0SIzbtl4fA",
                "position": 9
            },
            {
                "title": "Buy Genuine Nintendo GameBoy Pocket - Yellow at Ubuy India",
                "link": "https://www.ubuy.co.in/product/47MMJS77C-authentic-nintendo-gameboy-pocket-yellow-100-oem",
                "source": "www.ubuy.co.in",
                "original_thumbnail": "https://images-cdn.ubuy.co.in/665376d762bd1515ff2a0463-nintendo-gameboy-pocket-yellow-100.jpg",
                "thumbnail": "https://encrypted-tbn3.gstatic.com/images?q=tbn:ANd9GcQXmFkVcE4Ezg1cOAsRK_qumpzBzyIHCEsaw5D_h2wV8OY1r8mK",
                "tag": "₹15,406",
                "in_stock": "In stock",
                "position": 10
            },
            {
                "title": "Nintendo Gameboy Color",
                "link": "https://pi-india.in/shopdetail/29517322/",
                "source": "pi-india.in",
                "original_thumbnail": "https://u-mercari-images.mercdn.net/photos/m39573383110_1.jpg",
                "thumbnail": "https://encrypted-tbn2.gstatic.com/images?q=tbn:ANd9GcTxlHfLjrEEmduAl0c_b0JsCvBjfHNoTNaH_4xvmzanZ93UzBin",
                "position": 11
            },
            {
                "title": "tobegamed on eBay",
                "link": "https://www.ebay.com.sg/usr/tobegamed?_trksid=p4429486.m3561.l49544",
                "source": "www.ebay.com.sg",
                "original_thumbnail": "https://i.ebayimg.com/images/g/BecAAeSwr9dobp84/s-l300.jpg",
                "thumbnail": "https://encrypted-tbn2.gstatic.com/images?q=tbn:ANd9GcSYS43aK4aNZyaeWf8-xaHbpUtnBiNMUKX3MKF4tZlbEVWsOgKg",
                "position": 12
            },
            {
                "title": "Nintendo Game Boy Color PAL Video Game Handheld Systems for sale | eBay",
                "link": "https://www.ebay.ie/b/bn_7028489722",
                "source": "www.ebay.ie",
                "original_thumbnail": "https://i.ebayimg.com/images/g/1dYAAeSwZTVoSvJ1/s-l225.jpg",
                "thumbnail": "https://encrypted-tbn1.gstatic.com/images?q=tbn:ANd9GcTf83LCML_4f2V6LpExZJMznWe8NdRi09HkPWpChx8TsA2fnBC1",
                "position": 13
            },
            {
                "title": "Nintendo Gameboy Color GBC extra IPS screen Backlight Custom Game Boy Japan JP | eBay",
                "link": "https://www.ebay.com.my/itm/385356672879",
                "source": "www.ebay.com.my",
                "original_thumbnail": "https://i.ebayimg.com/images/g/TVIAAOSwyaBjxe77/s-l400.jpg",
                "thumbnail": "https://encrypted-tbn1.gstatic.com/images?q=tbn:ANd9GcR_9OIM4HhxDHEaDk4dzEPrgTRSgLmrOkFTnKg35CReKKgQyd5Q",
                "position": 14
            },
            {
                "title": "Nintendo Gameboy Color Yellow Console - Baxtros",
                "link": "https://baxtros.co.uk/product/nintendo-gameboy-color-yellow-console/",
                "source": "baxtros.co.uk",
                "original_thumbnail": "https://baxtros.co.uk/wp-content/uploads/2016/10/DSC_1114-3-150x150.jpg",
                "thumbnail": "https://encrypted-tbn3.gstatic.com/images?q=tbn:ANd9GcR4ne4soULTACCh3RXJTrpR2S6iqN8GncU9fIBmS9v1bfS3j47T",
                "position": 15
            },
            {
                "title": "*NEW GLASS SCREEN* Nintendo Game Boy Color GBC Dandelion Yellow System NEW | eBay",
                "link": "https://www.ebay.com/itm/191709821062",
                "source": "www.ebay.com",
                "original_thumbnail": "https://i.ebayimg.com/images/g/htIAAOSwMgdX1aHp/s-l400.jpg",
                "thumbnail": "https://encrypted-tbn0.gstatic.com/images?q=tbn:ANd9GcTfB8clGS-2Hj8FTsmytcj8AFwjNbJp3p5wHgoKXOy1QYwm8P-Q",
                "position": 16
            },
            {
                "title": "GameBoy - Trump Collection Cartridge + Booklet Japan | eBay Australia",
                "link": "https://www.ebay.com.au/itm/174839901768",
                "source": "www.ebay.com.au",
                "original_thumbnail": "https://i.ebayimg.com/images/g/1owAAOSwMstg7tr9/s-l400.jpg",
                "thumbnail": "https://encrypted-tbn3.gstatic.com/images?q=tbn:ANd9GcTGDb6eP_VjFBk4Q3IK6Yjma_HnljGZ5mfiua9iZN9K-fOwORbH",
                "position": 17
            },
            {
                "title": "Nintendo GameBoy Color Handheld System Yellow With Kirbys Dream Land Bag! | eBay",
                "link": "https://www.ebay.com/itm/326303963319",
                "source": "www.ebay.com",
                "original_thumbnail": "https://i.ebayimg.com/images/g/AuwAAOSwmpJnDSQ-/s-l400.jpg",
                "thumbnail": "https://encrypted-tbn1.gstatic.com/images?q=tbn:ANd9GcQAfj4wxRc_gOrJcTlHnYlJu2zjfvdfEyPzpfYot_fVSFf_NJ3-",
                "position": 18
            },
            {
                "title": "Nintendo Game Boy Color, Unused, Rare, Yellow, with Box & Instructions. | eBay",
                "link": "https://www.ebay.com/itm/256594372980",
                "source": "www.ebay.com",
                "original_thumbnail": "https://i.ebayimg.com/images/g/XiEAAOSw7ihll9w8/s-l400.jpg",
                "thumbnail": "https://encrypted-tbn0.gstatic.com/images?q=tbn:ANd9GcQyyYojo9bCR5Ekk9Yl8Pgl98VoS0FwQi3QLtCKTZapczAFVivL",
                "position": 19
            },
            {
                "title": "Vintage Gameboy Color | eBay",
                "link": "https://www.ebay.com/shop/vintage-gameboy-color?_nkw=vintage+gameboy+color",
                "source": "www.ebay.com",
                "original_thumbnail": "https://i.ebayimg.com/images/g/W6UAAOSwupxn~Xco/s-l300.jpg",
                "thumbnail": "https://encrypted-tbn2.gstatic.com/images?q=tbn:ANd9GcRNSXndwjbjLf-s4uuvNqzpYOFbeyfY4CTWTBUVT8jLbUQ9ZTlg",
                "position": 20
            },
            {
                "title": "Nintendo Game Boy Color Handheld System - Dandelion for sale online | eBay Australia",
                "link": "https://www.ebay.com.au/p/100236341",
                "source": "www.ebay.com.au",
                "original_thumbnail": "https://i.ebayimg.com/images/g/R4YAAOSwasBoFr~C/s-l225.jpg",
                "thumbnail": "https://encrypted-tbn1.gstatic.com/images?q=tbn:ANd9GcTkohGcPorZgZLa6TAg-yNDdYfNObXvqC13cJQgu7uEoEclDtHj",
                "position": 21
            },
            {
                "title": "Nintendo Gameboy Color Console Dandelion Yellow - Tested And Working | eBay",
                "link": "https://www.ebay.com/itm/126030940251",
                "source": "www.ebay.com",
                "original_thumbnail": "https://i.ebayimg.com/images/g/2-0AAOSwUXFkwxed/s-l1200.jpg",
                "thumbnail": "https://encrypted-tbn2.gstatic.com/images?q=tbn:ANd9GcQ79z2XzwsicCyIQaxJEn9QP_W-VB6Wgp6LQ5HvSGkiQp-d7vsb",
                "position": 22
            },
            {
                "title": "Nintendo Game Boy Color Multicolor Consoles for sale | eBay",
                "link": "https://www.ebay.com/b/Nintendo-Game-Boy-Color-Multicolor-Consoles/139971/bn_109358248",
                "source": "www.ebay.com",
                "original_thumbnail": "https://i.ebayimg.com/images/g/VLgAAeSwiC5oeHPV/s-l225.jpg",
                "thumbnail": "https://encrypted-tbn3.gstatic.com/images?q=tbn:ANd9GcRmrudzpCDwVD3tkFnBi8nVIgAwa5j8cbZVTltBS9YYKQHsBXE6",
                "position": 23
            },
            {
                "title": "GAMEBOY COLOR Super Robot Wars D Super Robot Wars K | Buy&Ship MY | Shop Worldwide and Ship Malaysia",
                "link": "https://www.buyandship.com.my/mercari/products/m27303329699/",
                "source": "www.buyandship.com.my",
                "original_thumbnail": "https://static.mercdn.net/item/detail/orig/photos/m27303329699_4.jpg?1754047392",
                "thumbnail": "https://encrypted-tbn3.gstatic.com/images?q=tbn:ANd9GcSOzxUBEKyaDFoD1sF5vlSBfNBXgHCZ4iGncuhGD0l7B4S-plZi",
                "tag": "¥7,800",
                "position": 24
            },
            {
                "title": "Nintendo Gameboy Color | eBay",
                "link": "https://www.ebay.at/sch/i.html?_sacat=0&_nkw=nintendo+gameboy+color&_frs=1",
                "source": "www.ebay.at",
                "original_thumbnail": "https://i.ebayimg.com/images/g/a6QAAeSwUJpodc0y/s-l300.jpg",
                "thumbnail": "https://encrypted-tbn3.gstatic.com/images?q=tbn:ANd9GcTRluJm6enKbksk9Q57vaCcZMmD0Dc2TXXKLd3KnXewqqKUy-vg",
                "position": 25
            },
            {
                "title": "GameBoy Color at Nes Bozz",
                "link": "https://bozz.dk/gameboy-color-138/",
                "source": "bozz.dk",
                "original_thumbnail": "https://bozz.dk/media/cache/category_children_thumb/category-images/14/0/gbcgul1473944268.jpg?1473944268",
                "thumbnail": "https://encrypted-tbn3.gstatic.com/images?q=tbn:ANd9GcQwVf6x5rm5J2bWb5CKgmEcv1jsgqyaKUmJpRVwybFeVRvngMGf",
                "position": 26
            },
            {
                "title": "Nintendo game boy Cut Out Stock Images & Pictures - Alamy",
                "link": "https://www.alamy.com/stock-photo/nintendo-game-boy.html?cutout=1",
                "source": "www.alamy.com",
                "original_thumbnail": "https://l450v.alamy.com/450v/d1xr9t/nintendo-game-boy-colour-d1xr9t.jpg",
                "thumbnail": "https://encrypted-tbn2.gstatic.com/images?q=tbn:ANd9GcS-1QAKFk2aaguNXUP_sMAPetBJHItLxa40DeSVLKeCL5zYrhDx",
                "position": 27
            },
            {
                "title": "SerialBoy TV Remote - YouTube",
                "link": "https://www.youtube.com/watch?v=5Egudrfi2v0",
                "source": "www.youtube.com",
                "original_thumbnail": "https://i.ytimg.com/vi/5Egudrfi2v0/hq720.jpg?sqp=-oaymwE7CK4FEIIDSFryq4qpAy0IARUAAAAAGAElAADIQj0AgKJD8AEB-AHOBYACgAqKAgwIABABGHIgVCg5MA8=&rs=AOn4CLB8j8WYX35B655FJLHvtuNifwtUHA",
                "thumbnail": "https://encrypted-tbn1.gstatic.com/images?q=tbn:ANd9GcTHbl7FEj6eHH--B7k5E6upPLM7OsMrH6M-W91-SUjEoajMSUWZ",
                "position": 28
            },
            {
                "title": "Beracah Worm Screen Light for Nintendo Gameboy Color Nepal | Ubuy",
                "link": "https://www.nepal.ubuy.com/en/product/1PVJY2VKW-beracah-reg-worm-screen-light-for-nintendo-gbc-gameboy-color",
                "source": "www.nepal.ubuy.com",
                "original_thumbnail": "https://www.nepal.ubuy.com/productimg/?image=aHR0cHM6Ly9pbWFnZXMtbmEuc3NsLWltYWdlcy1hbWF6b24uY29tL2ltYWdlcy9JLzQxUXVnTExiMnpMLl9TUzQwMF8uanBn.jpg",
                "thumbnail": "https://encrypted-tbn2.gstatic.com/images?q=tbn:ANd9GcRHWnem9nZyPigLwCgzH_NVnSgjIWWlnSyqoH_7bmGZgkjNarK9",
                "position": 29
            },
            {
                "title": "Orginal nintendo game boy color. two games full package | eBay",
                "link": "https://www.ebay.com/itm/334761735971?_ul=IL",
                "source": "www.ebay.com",
                "original_thumbnail": "https://i.ebayimg.com/images/g/CrcAAOSwHpNj1Y3A/s-l400.jpg",
                "thumbnail": "https://encrypted-tbn1.gstatic.com/images?q=tbn:ANd9GcTtWJ1tfE3X9kA07fEnn36RUTlkHU2t-LaOFJLBNb44DV3bGoOy",
                "tag": "£150",
                "in_stock": "In stock",
                "position": 30
            },
            {
                "title": "Stream Capital-Gold music | Listen to songs, albums, playlists for free on SoundCloud",
                "link": "https://soundcloud.com/user-729341119",
                "source": "soundcloud.com",
                "original_thumbnail": "https://i1.sndcdn.com/avatars-000311944381-y5de7l-t240x240.jpg",
                "thumbnail": "https://encrypted-tbn1.gstatic.com/images?q=tbn:ANd9GcSohwv4S8CKnFNqiBDjcIWhs7z8GQtAMPzshg49P-MPoK3jRSSK",
                "position": 31
            },
            {
                "title": "Gameboy Color for sale | eBay",
                "link": "https://www.ebay.ca/sch/i.html?_nkw=gameboy+color&Brand=&_dcat=139971",
                "source": "www.ebay.ca",
                "original_thumbnail": "https://i.ebayimg.com/images/g/wCkAAOSwm7ln~es5/s-l300.jpg",
                "thumbnail": "https://encrypted-tbn0.gstatic.com/images?q=tbn:ANd9GcS3QRM9US8XT3-4m5e1y63_Q0uJfS7xaoQRjxVweEm0vIHz0UoE",
                "position": 32
            },
            {
                "title": "13. Juli 2025 - YouTube",
                "link": "https://www.youtube.com/shorts/KJkgBmuMoD0",
                "source": "www.youtube.com",
                "original_thumbnail": "https://i.ytimg.com/vi/KJkgBmuMoD0/mqdefault.jpg",
                "thumbnail": "https://encrypted-tbn0.gstatic.com/images?q=tbn:ANd9GcSR1Ud7t3dBknk09BZgsm1AR4oErUro9r8k-Q4zflXHlwOI-IBp",
                "position": 33
            },
            {
                "title": "All products | Retrogame Tycoon -",
                "link": "https://retrogametycoon.com/en/catalogue/?q=&sort_by=date_stocked&selected_facets=console_exact:GBC&selected_facets=console_exact:Retropelit&page=4",
                "source": "retrogametycoon.com",
                "original_thumbnail": "https://retrogametycoon.com/media/cache/6b/3d/6b3df0ac96267db3d35c88992c0a9831.jpg",
                "thumbnail": "https://encrypted-tbn2.gstatic.com/images?q=tbn:ANd9GcRLmjcOjKPJsFgD06ezNrTmWXjkemu90ziTVThb2sMv7AcrJneJ",
                "position": 34
            },
            {
                "title": "Nintendo Game Boy Color Yellow Bundle | eBay",
                "link": "https://www.ebay.it/itm/353612437473",
                "source": "www.ebay.it",
                "original_thumbnail": "https://i.ebayimg.com/images/g/sLoAAOSw2nNgDiwA/s-l400.jpg",
                "thumbnail": "https://encrypted-tbn0.gstatic.com/images?q=tbn:ANd9GcR_FFBtBsfWF7Fpt8KE7CF1bftZvJtTknb5Izcq99IVkhDAFgze",
                "tag": "$160",
                "in_stock": "In stock",
                "position": 35
            },
            {
                "title": "Gameboy colour” For Sale | Toys & Games | Carousell Singapore",
                "link": "https://www.carousell.sg/hobbies-toys/toys-games/gameboy-colour/q-12/",
                "source": "www.carousell.sg",
                "original_thumbnail": "https://media.karousell.com/media/photos/products/2015/11/15/184406_34502378_thumbnail.jpg",
                "thumbnail": "https://encrypted-tbn0.gstatic.com/images?q=tbn:ANd9GcSKRev1sIjsq1nWuCGQeVTel6iTaYGcvAnWe-eOZolZSfPuC5r9",
                "position": 36
            },
            {
                "title": "Nintendo Game Boy Color - Dandelion Yellow for Sale in Lake View Terrace, CA - OfferUp",
                "link": "https://offerup.com/item/detail/a72709f2-86b5-3cd3-8ab0-99dea0f58ed5",
                "source": "offerup.com",
                "original_thumbnail": "https://images.offerup.com/zsdvnI3DArHTkhjOLI5IUnw9Js0=/567x1008/27fc/27fc64904d1a4725aaa96d095c906e3d.jpg",
                "thumbnail": "https://encrypted-tbn2.gstatic.com/images?q=tbn:ANd9GcTEzLeSh_U3puUCih-aWPcbvFvCo_uIWm_IiqwMxqfPowQ-PjXD",
                "position": 37
            },
            {
                "title": "Buy Authentic Nintendo Game Boy Color - Yellow at Ubuy Singapore",
                "link": "https://www.ubuy.com.sg/product/7G0WY8FK8-nintendo-gameboy-game-boy-color-yellow-authentic",
                "source": "www.ubuy.com.sg",
                "original_thumbnail": "https://i5.walmartimages.com/seo/Nintendo-GameBoy-Game-Boy-Color-Yellow-Authentic_3a19aa85-d854-4a37-865e-c41031f82a8c.6eba3bd0fc7db876e3aaeaf919fa6a5c.jpeg?odnWidth=180&odnHeight=180&odnBg=ffffff",
                "thumbnail": "https://encrypted-tbn1.gstatic.com/images?q=tbn:ANd9GcQjHxGPO3206qU7hiKNjZEl00DOV5lEwNI4RUeE78HNuIkAW9kE",
                "position": 38
            },
            {
                "title": "OEM Used Nintendo GBC Housing Shell – Choose Your Color front & back | eBay",
                "link": "https://www.ebay.com/itm/375492995612",
                "source": "www.ebay.com",
                "original_thumbnail": "https://i.ebayimg.com/images/g/L8UAAOSwwsNmccx9/s-l400.jpg",
                "thumbnail": "https://encrypted-tbn3.gstatic.com/images?q=tbn:ANd9GcRKuBWThdfFm8hFrYMQT3rUi748eNIq_YCxZycAe2HZa_8dwx4p",
                "position": 39
            },
            {
                "title": "Nintendo Gameboy Color | Shopee Malaysia",
                "link": "https://shopee.com.my/Nintendo-Gameboy-Color-i.232650656.22433556350",
                "source": "shopee.com.my",
                "original_thumbnail": "https://down-my.img.susercontent.com/file/my-11134207-23030-394xts89lwovb9",
                "thumbnail": "https://encrypted-tbn0.gstatic.com/images?q=tbn:ANd9GcRddF20OUJ1AYVj0wI-vdmb7MMOMB67kgotv8gql8cuDNzBoKzG",
                "position": 40
            },
            {
                "title": "Nintendo Gameboy Colour *New Backlit IPS Screen* CGB-001 Yellow CGB-001 | eBay UK",
                "link": "https://www.ebay.co.uk/itm/388429710005",
                "source": "www.ebay.co.uk",
                "original_thumbnail": "https://i.ebayimg.com/images/g/Kq8AAeSwrdtn~fxU/s-l400.jpg",
                "thumbnail": "https://encrypted-tbn1.gstatic.com/images?q=tbn:ANd9GcQg-J0eA28s-ThvuBPkUp47YPXDpMgUlIOeyOSO8E2fxE521qX2",
                "tag": "A$250",
                "in_stock": "In stock",
                "position": 41
            },
            {
                "title": "Nintendo Game Boy Colour / Color in original box",
                "link": "https://www.galactictraders.co.za/retro/12429-nintendo-game-boy-colour-color-in-original-box.html",
                "source": "www.galactictraders.co.za",
                "original_thumbnail": "https://www.galactictraders.co.za/26764-home_default/nintendo-game-boy-colour-color-in-original-box.jpg",
                "thumbnail": "https://encrypted-tbn2.gstatic.com/images?q=tbn:ANd9GcTml9gtixA29asDjGiXCq45Xn9hpWTJcpOVjs9J8nRZZN4hy1cT",
                "position": 42
            },
            {
                "title": "Gameboy color deals retail price",
                "link": "https://www.gcmi.org/?g=76102517",
                "source": "www.gcmi.org",
                "original_thumbnail": "https://i.ebayimg.com/images/g/39wAAOSwcz1kNVJq/s-l1200.jpg",
                "thumbnail": "https://encrypted-tbn3.gstatic.com/images?q=tbn:ANd9GcTYu8HdupkQFunl8Kqfh6k_Re4RUr-Kqd9tlsl3ryR-wMAQh6ke",
                "position": 43
            },
            {
                "title": "Nanoloop 1.2 Cartridge and yellow Game Boy Color | Reverb",
                "link": "https://reverb.com/item/26891146-nanoloop-1-2-cartridge-and-yellow-game-boy-color",
                "source": "reverb.com",
                "original_thumbnail": "https://rvb-img.reverb.com/image/upload/s--ZBwxzQHM--/a_270/t_card-square/v1565727766/xovtobyepremc6vtbhzb.jpg",
                "thumbnail": "https://encrypted-tbn3.gstatic.com/images?q=tbn:ANd9GcRixmrM9Kzoc_7QLq4LK1X-e-ayTBq0Xp_0TpLkphQ8M7jhuKnA",
                "tag": "$100",
                "in_stock": "In stock",
                "position": 44
            },
            {
                "title": "Nintendo Game Boy Color - Yellow 45496710439 | eBay UK",
                "link": "https://www.ebay.co.uk/itm/145955583165",
                "source": "www.ebay.co.uk",
                "original_thumbnail": "https://i.ebayimg.com/images/g/KtIAAOSwRdxmv2zR/s-l400.jpg",
                "thumbnail": "https://encrypted-tbn3.gstatic.com/images?q=tbn:ANd9GcQE7jS11AhVMhQ8voywvHA4lfcRnnSkKLihWvpe22ivogg9Z3kp",
                "position": 45
            },
            {
                "title": "Game boy color and two games for Sale in Richmond, VA - OfferUp",
                "link": "https://offerup.com/item/detail/e7e1b67f-e5ed-3657-950c-62c45f4b32b2",
                "source": "offerup.com",
                "original_thumbnail": "https://images.offerup.com/hyV4xNh0Fri543XLYYJUh3xkwVs=/250x333/d384/d3841a34f7cf4c568d291c6b972d22ea.jpg",
                "thumbnail": "https://encrypted-tbn2.gstatic.com/images?q=tbn:ANd9GcQKW-CPUWKMzObX6U-nuDALVLO6iu3vJYXMqIHqKAKhJvf3FiTU",
                "position": 46
            },
            {
                "title": "NINTENDO GAMEBOY COLOR POKEMON PIKACHU VERSION EXCELLENT LIKE NEW CONDITION Consoles",
                "link": "https://www.gmcmiraj.edu.in/267864016.htm",
                "source": "www.gmcmiraj.edu.in",
                "original_thumbnail": "https://u-mercari-images.mercdn.net/photos/m55940966728_2.jpg",
                "thumbnail": "https://encrypted-tbn3.gstatic.com/images?q=tbn:ANd9GcTDP12wQ6w47eO1DtFcyJsJC87FjKU2SACXmPe_yP6OeUSAOjb6",
                "position": 47
            },
            {
                "title": "Dragon Warrior Action & Adventure Nintendo Video Games for sale | eBay",
                "link": "https://www.ebay.com/b/Dragon-Warrior-Action-Adventure-Nintendo-Video-Games/139973/bn_91178857",
                "source": "www.ebay.com",
                "original_thumbnail": "https://i.ebayimg.com/images/g/B7cAAeSwpzloK9LI/s-l225.jpg",
                "thumbnail": "https://encrypted-tbn0.gstatic.com/images?q=tbn:ANd9GcQySaPRCpaG3h1xRd0wmYIQU3imODQoAKk6UE5rMRkNYmuVsmu-",
                "position": 48
            },
            {
                "title": "Nintendo Game Boy Color Giallo - Retrogaming & Toys",
                "link": "https://www.retrogamingandtoys.it/it/prodotto/videogames-it/nintendo-it-videogames-it/nintendo-game-boy-color-it/console-it-nintendo-game-boy-color-it/nintendo-game-boy-color-giallo/",
                "source": "www.retrogamingandtoys.it",
                "original_thumbnail": "https://www.retrogamingandtoys.it/wp-content/uploads/2024/03/31175-thickbox_default-Nintendo-Game-Boy-Pocket-Yellow-300x300-optimized.jpg",
                "thumbnail": "https://encrypted-tbn2.gstatic.com/images?q=tbn:ANd9GcTEY6R1ussjOH_xosurRw5bVi73D13aRReau4wxju8VCVI6yvYB",
                "position": 49
            },
            {
                "title": "First gen gameboy",
                "link": "https://www.greensafaris.com/?b=11903762999",
                "source": "www.greensafaris.com",
                "original_thumbnail": "https://u-mercari-images.mercdn.net/photos/m96683604863_1.jpg",
                "thumbnail": "https://encrypted-tbn1.gstatic.com/images?q=tbn:ANd9GcQU0-qGnbJ882yN8kzFKKZx0tuhTLfe_lRZZJgR33TzttSYwZUr",
                "position": 50
            },
            {
                "title": "Pikachu pokemon nintendo GIF - Find on GIFER",
                "link": "https://gifer.com/en/VdGO",
                "source": "gifer.com",
                "original_thumbnail": "https://i.gifer.com/origin/b9/b95f7f8980cbc0e46a65e31a3d5ac08e_w200.gif",
                "thumbnail": "https://encrypted-tbn3.gstatic.com/images?q=tbn:ANd9GcTEnRsPj276aA-wSKD6p9MjrCoKvTptv2rsAKj-pn8foOxR4j_n",
                "position": 51
            },
            {
                "title": "Vintage Nintendo Game Boy Color - Yellow",
                "link": "https://www.thehalfdone.com/shopdetail/18906287/",
                "source": "www.thehalfdone.com",
                "original_thumbnail": "https://u-mercari-images.mercdn.net/photos/m12009331373_6.jpg",
                "thumbnail": "https://encrypted-tbn1.gstatic.com/images?q=tbn:ANd9GcRPCsGxPkd13gSX7IVyfG-RSqAeQC9Icu72tEk9hfXkgwXxqoet",
                "position": 52
            },
            {
                "title": "Gameboy Color Yellow",
                "link": "https://www.damal.bel.tr/product/gameboy-color-yellow",
                "source": "www.damal.bel.tr",
                "original_thumbnail": "https://u-mercari-images.mercdn.net/photos/m98310163433_1.jpg",
                "thumbnail": "https://encrypted-tbn2.gstatic.com/images?q=tbn:ANd9GcQ728i8pUN3eEqriTEEdpv5kDQKxyw0NO_fEm9ptWi3HGrZO6Xy",
                "position": 53
            }
        ],
        "tokens": [
            "color",
            "nintendo",
            "game",
            "boy",
            "game boy",
            "gameboy",
            "yellow",
            "boy color",
            "gameboy color",
            "nintendo game",
            "nintendo gameboy",
            "color yellow",
            "games",
            "dandelion",
            "gbc",
            "console",
            "handheld",
            "system",
            "dandelion yellow",
            "buy",
            "screen",
            "new",
            "video",
            "color console",
            "box",
            "uk",
            "india",
            "cartridge",
            "ubuy",
            "colour",
            "glass",
            "replacement",
            "full",
            "housing",
            "shell",
            "housing shell",
            "nintendo gbc",
            "video games"
        ]
    }
}